pandas_redshift/__init__.py
pandas_redshift/core.py
pandas_redshift/redshift_reserve_words.txt
pandas_redshift-2.0.5.dist-info/LICENSE
pandas_redshift-2.0.5.dist-info/METADATA
pandas_redshift-2.0.5.dist-info/WHEEL
pandas_redshift-2.0.5.dist-info/top_level.txt
pandas_redshift-2.0.5.dist-info/RECORD
